snakedoc/__init__.py
snakedoc/_version.py
snakedoc/linkcode.py
snakedoc/smk.py
snakedoc-0.2.2.dist-info/METADATA
snakedoc-0.2.2.dist-info/WHEEL
snakedoc-0.2.2.dist-info/licenses/LICENSE
snakedoc-0.2.2.dist-info/RECORD
