Metadata-Version: 2.1
Name: snakedoc
Version: 0.2.2
Summary: A Sphinx extension for Snakemake
Project-URL: Documentation, https://github.com/smutch/snakedoc#readme
Project-URL: Issues, https://github.com/smutch/snakedoc/issues
Project-URL: Source, https://github.com/smutch/snakedoc
Author-email: Simon Mutch <smutch@unimelb.edu.au>
License-Expression: MIT
License-File: LICENSE
Classifier: Development Status :: 4 - Beta
Classifier: Programming Language :: Python
Classifier: Programming Language :: Python :: 3.8
Classifier: Programming Language :: Python :: 3.9
Classifier: Programming Language :: Python :: 3.10
Classifier: Programming Language :: Python :: 3.11
Classifier: Programming Language :: Python :: 3.12
Classifier: Programming Language :: Python :: Implementation :: CPython
Requires-Python: >=3.8
Requires-Dist: snakemake>=7.6.2
Requires-Dist: sphinx<8,>=5
